gql_subscriptions/__init__.py
gql_subscriptions/__version__.py
gql_subscriptions/engine.py
gql_subscriptions/pubsub.py
gql_subscriptions/pubsubs/__init__.py
gql_subscriptions/pubsubs/redis.py
gql_subscriptions/with_filter.py
gql_subscriptions-0.0.3.dist-info/LICENSE
gql_subscriptions-0.0.3.dist-info/WHEEL
gql_subscriptions-0.0.3.dist-info/METADATA
gql_subscriptions-0.0.3.dist-info/RECORD
