Metadata-Version: 2.1
Name: gql-subscriptions
Version: 0.0.3
Summary: A Python3.7+ port of Apollo Graphql Subscriptions.
Home-page: https://github.com/syfun/gql-subscriptions
License: MIT
Author: ysun
Author-email: sunyu418@gmail.com
Requires-Python: >=3.7
Classifier: License :: OSI Approved :: MIT License
Classifier: Programming Language :: Python :: 3
Classifier: Programming Language :: Python :: 3.7
Classifier: Programming Language :: Python :: 3.8
Provides-Extra: redis
Requires-Dist: aioredis (>=1.3); extra == "redis"
Requires-Dist: typing_extensions (>=3.7.4,<4.0.0); python_version < "3.8"
